byte_formatter/__init__.py
byte_formatter/cli.py
byte_formatter/formatter.py
byte_formatter-0.0.2.dist-info/LICENSE
byte_formatter-0.0.2.dist-info/METADATA
byte_formatter-0.0.2.dist-info/WHEEL
byte_formatter-0.0.2.dist-info/entry_points.txt
byte_formatter-0.0.2.dist-info/RECORD
