Metadata-Version: 2.1
Name: byte-formatter
Version: 0.0.2
Summary: A Python project for formatting bytes
Home-page: https://github.com/rmkane/byte-formatter
License: MIT
Keywords: byte,formatter,cli
Author: Ryan Kane
Author-email: rmkane@proton.me
Requires-Python: >=3.7,<4.0
Classifier: Development Status :: 3 - Alpha
Classifier: Intended Audience :: Developers
Classifier: License :: OSI Approved :: MIT License
Classifier: Operating System :: OS Independent
Classifier: Programming Language :: Python :: 3
Classifier: Programming Language :: Python :: 3.7
Classifier: Programming Language :: Python :: 3.8
Classifier: Programming Language :: Python :: 3.9
Classifier: Programming Language :: Python :: 3.10
Classifier: Programming Language :: Python :: 3.11
Classifier: Programming Language :: Python :: 3.12
Classifier: Topic :: Software Development :: Build Tools
Requires-Dist: click (>=8.0,<9.0)
Project-URL: Documentation, https://github.com/rmkane/byte-formatter
Project-URL: Repository, https://github.com/rmkane/byte-formatter
